Part2/FSM.v
// ============================================================================
// Experiment 14 - Part 2
// Obfuscated FSM: 5-bit unlock sequence + blackhole state
// Group: 1
// Key: 5'b10001
// ============================================================================
`timescale 1ns/1ps

module FSM(
    input  x,
    input  clk,
    output reg out
);

    // ------------------------------------------------------------------------
    // Key sequence P1..P5 for GROUP 1
    // Key: 10001
    // ------------------------------------------------------------------------
    localparam P1 = 1'b1;  // MSB
    localparam P2 = 1'b0;
    localparam P3 = 1'b0;
    localparam P4 = 1'b0;
    localparam P5 = 1'b1;  // LSB

    // ------------------------------------------------------------------------
    // State encoding
    // ------------------------------------------------------------------------
    reg [3:0] state;

    // Original FSM (blue) states
    localparam S0_N = 4'b0000;
    localparam S1_N = 4'b0001;
    localparam S2_N = 4'b0010;
    localparam S3_N = 4'b0011;
    localparam S4_N = 4'b0100;

    // Obfuscation (orange) states
    localparam S0_O = 4'b1000; // start state on power-up
    localparam S1_O = 4'b1001;
    localparam S2_O = 4'b1010;
    localparam S3_O = 4'b1011;
    localparam S4_O = 4'b1100;

    // Blackhole state
    localparam BLACKHOLE = 4'b1111;

    // Initial state = obfuscation start
    initial begin
        state = S0_O;
        out   = 1'b0;
    end

    // ------------------------------------------------------------------------
    // Sequential logic
    // ------------------------------------------------------------------------
    always @(posedge clk) begin
        case (state)

            // ------------------------------------------------------------
            // Obfuscation FSM
            // ------------------------------------------------------------
            S0_O: begin
                out <= 1'b0;
                if (x == P1) state <= S1_O;
                else         state <= BLACKHOLE;
            end

            S1_O: begin
                out <= 1'b0;
                if (x == P2) state <= S2_O;
                else         state <= BLACKHOLE;
            end

            S2_O: begin
                out <= 1'b0;
                if (x == P3) state <= S3_O;
                else         state <= BLACKHOLE;
            end

            S3_O: begin
                out <= 1'b0;
                if (x == P4) state <= S4_O;
                else         state <= BLACKHOLE;
            end

            S4_O: begin
                out <= 1'b0;
                if (x == P5) state <= S0_N;  // Unlock: Jump to Original FSM
                else         state <= BLACKHOLE;
            end

            // ------------------------------------------------------------
            // Blackhole
            // ------------------------------------------------------------
            BLACKHOLE: begin
                state <= BLACKHOLE; // Stuck here forever
                out   <= 1'b0;
            end

            // ------------------------------------------------------------
            // Original FSM behavior
            // ------------------------------------------------------------
            S0_N: begin
                out <= 1'b0;
                if (x == 1'b1) state <= S2_N;
                else           state <= S1_N;
            end

            S1_N: begin
                out <= 1'b0;
                if (x == 1'b1) state <= S2_N;
                else           state <= S3_N;
            end

            S2_N: begin
                out <= 1'b0;
                if (x == 1'b1) state <= S4_N;
                else           state <= S3_N;
            end

            S3_N: begin
                out   <= 1'b0;
                state <= S4_N;
            end

            S4_N: begin
                if (x == 1'b1) begin
                    state <= S0_N;
                    out   <= 1'b1;
                end else begin
                    state <= S1_N;
                    out   <= 1'b0;
                end
            end

            // ------------------------------------------------------------
            // Default
            // ------------------------------------------------------------
            default: begin
                state <= S0_O;
                out   <= 1'b0;
            end
        endcase
    end

endmodule

Part2/tb_FSM.v
// ============================================================================
// Testbench for Obfuscated FSM (Part 2) - Group 1 FIXED
// ============================================================================

`timescale 1ns/1ps

module tb_FSM;

    reg clk;
    reg x;
    wire out;

    // DUT
    FSM dut (
        .x  (x),
        .clk(clk),
        .out(out)
    );

    // ------------------------------------------------------------------------
    // VCD dump
    // ------------------------------------------------------------------------
    initial begin
        $dumpfile("fsm_obf.vcd");
        $dumpvars(0, tb_FSM);
        $dumpvars(0, tb_FSM.dut); // Dump internal signals (state)
    end

    // ------------------------------------------------------------------------
    // Clock: 10 ns period
    // ------------------------------------------------------------------------
    initial begin
        clk = 1'b0;
        forever #5 clk = ~clk;
    end

    // ------------------------------------------------------------------------
    // Group 1 Key bits (Matches FSM.v)
    // ------------------------------------------------------------------------
    localparam P1 = 1'b1; 
    localparam P2 = 1'b0;
    localparam P3 = 1'b0;
    localparam P4 = 1'b0;
    localparam P5 = 1'b1;

    // Construct the vector for easier logical negation in tests
    localparam [4:0] P = {P1,P2,P3,P4,P5}; 
    localparam [3:0] S0_O = 4'b1000;

    // ------------------------------------------------------------------------
    // Task: reset FSM back to S0_O (Simulation force)
    // FIXED: Removed the #10 delay and x=0 to prevent "Blackhole trap"
    // ------------------------------------------------------------------------
    task reset_fsm;
    begin
        // Force state back to start
        dut.state = S0_O; 
        // We do NOT wait here. We let apply_sequence set 'x' immediately.
    end
    endtask

    // ------------------------------------------------------------------------
    // Task: apply a 5-bit sequence (MSB first)
    // ------------------------------------------------------------------------
    task apply_sequence(input [4:0] seq);
        integer i;
        begin
            for (i = 4; i >= 0; i = i - 1) begin
                x = seq[i]; // Apply bit
                #10;        // Wait one clock period
            end
            #10; // small gap after sequence
        end
    endtask

    // ------------------------------------------------------------------------
    // Main stimulus
    // ------------------------------------------------------------------------
    reg [4:0] seq;

    initial begin
        // Initialize x to avoid undefined state at start
        x = 0; 

        // -------------------------------------------------------
        // 1. Wrong key: All inverted (~P1..~P5)
        // -------------------------------------------------------
        #5; // Align away from time 0
        reset_fsm();
        seq = ~P;
        $display("Test 1: Wrong Key (All Inverted) = %b", seq);
        apply_sequence(seq);
        $display("        State after Test 1: %b (Expected 1111/Blackhole)", dut.state);

        // -------------------------------------------------------
        // 2. Wrong key: P1 correct, rest inverted
        // -------------------------------------------------------
        reset_fsm();
        seq = {P1, ~P2, ~P3, ~P4, ~P5};
        $display("Test 2: Wrong Key (P1 only)      = %b", seq);
        apply_sequence(seq);
        $display("        State after Test 2: %b (Expected 1111/Blackhole)", dut.state);

        // -------------------------------------------------------
        // 3. Wrong key: First 4 correct, last inverted
        // -------------------------------------------------------
        reset_fsm();
        seq = {P1, P2, P3, P4, ~P5};
        $display("Test 3: Wrong Key (Last bit wrong) = %b", seq);
        apply_sequence(seq);
        $display("        State after Test 3: %b (Expected 1111/Blackhole)", dut.state);

        // -------------------------------------------------------
        // 4. Correct Key: P1..P5
        // -------------------------------------------------------
        reset_fsm();
        seq = P;
        $display("Test 4: Correct Key                = %b", seq);
        apply_sequence(seq);
        $display("        State after Test 4: %b (Expected 0000/S0_N)", dut.state);

        // -------------------------------------------------------
        // Demonstrate Unlocked Behavior
        // -------------------------------------------------------
        // Since state should now be 0000 (S0_N), sending '1' should move it to S2_N (0010)
        x = 1; 
        #10;
        x = 0; 
        #10;
        
        #20;
        $finish;
    end

endmodule

Part2/fsm_obf.vcd
$date
	Tue Dec 16 23:43:27 2025
$end
$version
	Icarus Verilog
$end
$timescale
	1ps
$end
$scope module tb_FSM $end
$var wire 1 ! out $end
$var parameter 5 " P $end
$var parameter 1 # P1 $end
$var parameter 1 $ P2 $end
$var parameter 1 % P3 $end
$var parameter 1 & P4 $end
$var parameter 1 ' P5 $end
$var parameter 4 ( S0_O $end
$var reg 1 ) clk $end
$var reg 5 * seq [4:0] $end
$var reg 1 + x $end
$scope module dut $end
$var wire 1 ) clk $end
$var wire 1 + x $end
$var parameter 4 , BLACKHOLE $end
$var parameter 1 - P1 $end
$var parameter 1 . P2 $end
$var parameter 1 / P3 $end
$var parameter 1 0 P4 $end
$var parameter 1 1 P5 $end
$var parameter 4 2 S0_N $end
$var parameter 4 3 S0_O $end
$var parameter 4 4 S1_N $end
$var parameter 4 5 S1_O $end
$var parameter 4 6 S2_N $end
$var parameter 4 7 S2_O $end
$var parameter 4 8 S3_N $end
$var parameter 4 9 S3_O $end
$var parameter 4 : S4_N $end
$var parameter 4 ; S4_O $end
$var reg 1 ! out $end
$var reg 4 < state [3:0] $end
$upscope $end
$scope task apply_sequence $end
$var reg 5 = seq [4:0] $end
$var integer 32 > i [31:0] $end
$upscope $end
$scope task reset_fsm $end
$upscope $end
$upscope $end
$scope module tb_FSM $end
$scope module dut $end
$upscope $end
$upscope $end
$enddefinitions $end
$comment Show the parameter values. $end
$dumpall
b1100 ;
b100 :
b1011 9
b11 8
b1010 7
b10 6
b1001 5
b1 4
b1000 3
b0 2
11
00
0/
0.
1-
b1111 ,
b1000 (
1'
0&
0%
0$
1#
b10001 "
$end
#0
$dumpvars
bx >
bx =
b1000 <
0+
bx *
0)
0!
$end
#5000
b1111 <
b100 >
b1110 =
b1110 *
1)
#10000
0)
#15000
1)
1+
b11 >
#20000
0)
#25000
1)
b10 >
#30000
0)
#35000
1)
b1 >
#40000
0)
#45000
1)
0+
b0 >
#50000
0)
#55000
1)
b11111111111111111111111111111111 >
#60000
0)
#65000
1)
1+
b100 >
b11110 =
b11110 *
b1001 <
#70000
0)
#75000
b1111 <
1)
b11 >
#80000
0)
#85000
1)
b10 >
#90000
0)
#95000
1)
b1 >
#100000
0)
#105000
1)
0+
b0 >
#110000
0)
#115000
1)
b11111111111111111111111111111111 >
#120000
0)
#125000
1)
1+
b100 >
b10000 =
b10000 *
b1001 <
#130000
0)
#135000
b1010 <
1)
0+
b11 >
#140000
0)
#145000
b1011 <
1)
b10 >
#150000
0)
#155000
b1100 <
1)
b1 >
#160000
0)
#165000
b1111 <
1)
b0 >
#170000
0)
#175000
1)
b11111111111111111111111111111111 >
#180000
0)
#185000
1)
1+
b100 >
b10001 =
b10001 *
b1001 <
#190000
0)
#195000
b1010 <
1)
0+
b11 >
#200000
0)
#205000
b1011 <
1)
b10 >
#210000
0)
#215000
b1100 <
1)
b1 >
#220000
0)
#225000
b0 <
1)
1+
b0 >
#230000
0)
#235000
b10 <
1)
b11111111111111111111111111111111 >
#240000
0)
#245000
b100 <
1)
#250000
0)
#255000
b1 <
1)
0+
#260000
0)
#265000
b11 <
1)
#270000
0)
#275000
b100 <
1)
#280000
0)
#285000
b1 <
1)
